Metadata-Version: 2.4
Name: usingai39
Version: 0.1.0
Summary: A collection of AI-powered tools for games and apps.
Home-page: https://github.com/yhnujk/ai_tools_project.git
Author: Sang hyuck Won
Author-email: yhnujk@naver.com
Classifier: Programming Language :: Python :: 3.9
Classifier: License :: OSI Approved :: MIT License
Classifier: Operating System :: OS Independent
Requires-Python: ==3.9.*
Requires-Dist: Pillow<10.0.0,>=9.0.0
Requires-Dist: requests<3.0.0,>=2.20.0
Requires-Dist: openai<1.23.0,>=1.0.0
Requires-Dist: google-generativeai<0.3.2,>=0.2.0
Requires-Dist: python-dotenv<1.0.0,>=0.20.0
Dynamic: author
Dynamic: author-email
Dynamic: classifier
Dynamic: description
Dynamic: description-content-type
Dynamic: home-page
Dynamic: requires-dist
Dynamic: requires-python
Dynamic: summary
